snakemake_software_deployment_plugin_cvmfs/__init__.py
snakemake_software_deployment_plugin_cvmfs-0.2.3.dist-info/AUTHORS
snakemake_software_deployment_plugin_cvmfs-0.2.3.dist-info/LICENSE
snakemake_software_deployment_plugin_cvmfs-0.2.3.dist-info/METADATA
snakemake_software_deployment_plugin_cvmfs-0.2.3.dist-info/WHEEL
snakemake_software_deployment_plugin_cvmfs-0.2.3.dist-info/RECORD
