Metadata-Version: 2.3
Name: snakemake-software-deployment-plugin-cvmfs
Version: 0.2.3
Summary: A snakemake plugin to use CernVM-FS (cvmfs) as software deployment (backend)
Author: Izaskun Mallona
Author-email: izaskun.mallona@gmail.com
Requires-Python: >=3.11,<4.0
Classifier: Programming Language :: Python :: 3
Classifier: Programming Language :: Python :: 3.11
Classifier: Programming Language :: Python :: 3.12
Classifier: Programming Language :: Python :: 3.13
Requires-Dist: snakemake-interface-common (>=1.17.4,<2.0.0)
Requires-Dist: snakemake-interface-software-deployment-plugins (>=0.6.1,<0.7.0)
